xerror/__init__.py
xerror/api.py
xerror/cli.py
xerror/config.py
xerror/explainer.py
xerror/language_parsers.py
xerror/models.py
xerror/parser.py
xerror/rule_based_explainer.py
xerror/utils.py
xerror/watcher.py
xerror-1.0.0.dist-info/METADATA
xerror-1.0.0.dist-info/WHEEL
xerror-1.0.0.dist-info/entry_points.txt
xerror-1.0.0.dist-info/top_level.txt
xerror-1.0.0.dist-info/RECORD
