Metadata-Version: 2.4
Name: xerror
Version: 1.0.0
Summary: A smart CLI tool to analyze error logs from multiple languages and return AI-generated explanations and fix suggestions
Home-page: https://github.com/xerror/xerror
Author: Avishek Devnath
Author-email: avishekdevnath@gmail.com
Project-URL: Bug Reports, https://github.com/xerror/xerror/issues
Project-URL: Source, https://github.com/xerror/xerror
Project-URL: Documentation, https://github.com/xerror/xerror#readme
Keywords: error,debugging,ai,cli,python,traceback,exception
Classifier: Development Status :: 3 - Alpha
Classifier: Intended Audience :: Developers
Classifier: License :: OSI Approved :: MIT License
Classifier: Operating System :: OS Independent
Classifier: Programming Language :: Python :: 3
Classifier: Programming Language :: Python :: 3.10
Classifier: Programming Language :: Python :: 3.11
Classifier: Programming Language :: Python :: 3.12
Classifier: Topic :: Software Development :: Debuggers
Classifier: Topic :: Software Development :: Libraries :: Python Modules
Classifier: Topic :: System :: Logging
Requires-Python: >=3.10
Requires-Dist: click>=8.1.0
Requires-Dist: rich>=13.0.0
Requires-Dist: google-generativeai>=0.3.0
Requires-Dist: python-dotenv>=1.0.0
Requires-Dist: pathlib2>=2.3.0; python_version < "3.4"
Requires-Dist: pytest>=7.0.0
Requires-Dist: black>=23.0.0
Requires-Dist: flake8>=6.0.0
Dynamic: author
Dynamic: author-email
Dynamic: classifier
Dynamic: description
Dynamic: description-content-type
Dynamic: home-page
Dynamic: keywords
Dynamic: project-url
Dynamic: requires-dist
Dynamic: requires-python
Dynamic: summary
